LICENSE
MANIFEST.in
flashcards-complete.sh
setup.py
flashcards/__init__.py
flashcards/cards.py
flashcards/main.py
flashcards/sets.py
flashcards/storage.py
flashcards/study.py
flashcards/commands/__init__.py
flashcards/commands/cards.py
flashcards/commands/sets.py
flashcards/utils/__init__.py
flashcards/utils/storage.py
pyflashcards.egg-info/PKG-INFO
pyflashcards.egg-info/SOURCES.txt
pyflashcards.egg-info/dependency_links.txt
pyflashcards.egg-info/entry_points.txt
pyflashcards.egg-info/requires.txt
pyflashcards.egg-info/top_level.txt