Metadata-Version: 1.0
Name: pyflashcards
Version: 1.0.2
Summary: CLI application that focus on quickly creating study flash cards
Home-page: UNKNOWN
Author: Jonathan Lalande
Author-email: jonathan.lalande.1@ens.etsmtl.ca
License: MIT
Platform: UNKNOWN
